odoo10_addon_project_task_material_analytic_partner-10.0.1.0.0-py2.7-nspkg.pth
odoo/addons/project_task_material_analytic_partner/README.rst
odoo/addons/project_task_material_analytic_partner/__init__.py
odoo/addons/project_task_material_analytic_partner/__manifest__.py
odoo/addons/project_task_material_analytic_partner/i18n/de.po
odoo/addons/project_task_material_analytic_partner/i18n/es.po
odoo/addons/project_task_material_analytic_partner/i18n/es_MX.po
odoo/addons/project_task_material_analytic_partner/i18n/fi.po
odoo/addons/project_task_material_analytic_partner/i18n/fr.po
odoo/addons/project_task_material_analytic_partner/i18n/it.po
odoo/addons/project_task_material_analytic_partner/i18n/nl.po
odoo/addons/project_task_material_analytic_partner/i18n/pt.po
odoo/addons/project_task_material_analytic_partner/i18n/pt_BR.po
odoo/addons/project_task_material_analytic_partner/i18n/sl.po
odoo/addons/project_task_material_analytic_partner/models/__init__.py
odoo/addons/project_task_material_analytic_partner/models/project_task_material_analytic_partner.py
odoo/addons/project_task_material_analytic_partner/static/description/icon.png
odoo/addons/project_task_material_analytic_partner/tests/__init__.py
odoo/addons/project_task_material_analytic_partner/tests/test_project_task_material_analytic_partner.py
odoo/addons/project_task_material_analytic_partner/views/project_view.xml
odoo10_addon_project_task_material_analytic_partner-10.0.1.0.0.dist-info/DESCRIPTION.rst
odoo10_addon_project_task_material_analytic_partner-10.0.1.0.0.dist-info/METADATA
odoo10_addon_project_task_material_analytic_partner-10.0.1.0.0.dist-info/RECORD
odoo10_addon_project_task_material_analytic_partner-10.0.1.0.0.dist-info/WHEEL
odoo10_addon_project_task_material_analytic_partner-10.0.1.0.0.dist-info/metadata.json
odoo10_addon_project_task_material_analytic_partner-10.0.1.0.0.dist-info/namespace_packages.txt
odoo10_addon_project_task_material_analytic_partner-10.0.1.0.0.dist-info/top_level.txt
